colorlogx/__init__.py
colorlogx/logger.py
colorlogx-0.1.0.dist-info/METADATA
colorlogx-0.1.0.dist-info/WHEEL
colorlogx-0.1.0.dist-info/top_level.txt
colorlogx-0.1.0.dist-info/RECORD
