Metadata-Version: 2.4
Name: colorlogx
Version: 0.1.0
Summary: A simple colored and rotating daily logger
Author-email: Tobias Auer <colorlogx@t-auer.com>
License: MIT
Project-URL: Homepage, https://github.com/tobias-auer/colorlogx
